prefect_collection/__init__.py
prefect_collection/_version.py
prefect_collection/flows.py
prefect_collection/tasks.py
prefect_collection-0.2.1.dist-info/LICENSE
prefect_collection-0.2.1.dist-info/METADATA
prefect_collection-0.2.1.dist-info/WHEEL
prefect_collection-0.2.1.dist-info/top_level.txt
prefect_collection-0.2.1.dist-info/RECORD
