Metadata-Version: 2.1
Name: prefect-collection
Version: 0.2.1
Summary: Prefect Collection Template contains all the boilerplate that you need to create a Prefect collection.
Home-page: https://github.com/arthur_dent/prefect-collection
Author: Arthur Dent
Author-email: arthur.dent@example.com
License: Apache License 2.0
Keywords: prefect
Platform: UNKNOWN
Classifier: Natural Language :: English
Classifier: Intended Audience :: Developers
Classifier: Intended Audience :: System Administrators
Classifier: License :: OSI Approved :: Apache Software License
Classifier: Programming Language :: Python :: 3 :: Only
Classifier: Programming Language :: Python :: 3.7
Classifier: Programming Language :: Python :: 3.8
Classifier: Programming Language :: Python :: 3.9
Classifier: Topic :: Software Development :: Libraries
Requires-Python: >=3.7
License-File: LICENSE
Requires-Dist: prefect (>=2.0a9)
Provides-Extra: dev
Requires-Dist: pytest ; extra == 'dev'
Requires-Dist: black ; extra == 'dev'
Requires-Dist: flake8 ; extra == 'dev'
Requires-Dist: mypy ; extra == 'dev'
Requires-Dist: mkdocs ; extra == 'dev'
Requires-Dist: mkdocs-material ; extra == 'dev'
Requires-Dist: mkdocstrings ; extra == 'dev'
